{
  "120141": {
    "id": 120141,
    "hero1": 1205,
    "resetID": 101,
    "resetNum": 100
  },
  "120241": {
    "id": 120241,
    "hero1": 1201,
    "resetID": 101,
    "resetNum": 100
  },
  "120341": {
    "id": 120341,
    "hero1": 1302,
    "resetID": 101,
    "resetNum": 100
  },
  "120342": {
    "id": 120342,
    "hero1": 1505,
    "resetID": 101,
    "resetNum": 100
  },
  "120441": {
    "id": 120441,
    "hero1": 1104,
    "resetID": 101,
    "resetNum": 100
  },
  "120442": {
    "id": 120442,
    "hero1": 1205,
    "resetID": 101,
    "resetNum": 100
  },
  "120541": {
    "id": 120541,
    "hero1": 1206,
    "resetID": 101,
    "resetNum": 100
  },
  "120542": {
    "id": 120542,
    "hero1": 1207,
    "resetID": 101,
    "resetNum": 100
  },
  "120561": {
    "id": 120561,
    "hero1": 1309,
    "resetID": 101,
    "resetNum": 100
  },
  "120641": {
    "id": 120641,
    "hero1": 1202,
    "resetID": 101,
    "resetNum": 100
  },
  "120741": {
    "id": 120741,
    "hero1": 1205,
    "resetID": 101,
    "resetNum": 100
  },
  "120941": {
    "id": 120941,
    "hero1": 1201,
    "resetID": 101,
    "resetNum": 100
  },
  "121041": {
    "id": 121041,
    "hero1": 1319,
    "resetID": 101,
    "resetNum": 100
  },
  "121441": {
    "id": 121441,
    "hero1": 1205,
    "resetID": 101,
    "resetNum": 100
  },
  "121541": {
    "id": 121541,
    "hero1": 1216,
    "resetID": 101,
    "resetNum": 100
  },
  "121641": {
    "id": 121641,
    "hero1": 1215,
    "resetID": 101,
    "resetNum": 100
  },
  "121741": {
    "id": 121741,
    "hero1": 1216,
    "resetID": 101,
    "resetNum": 100
  },
  "130141": {
    "id": 130141,
    "hero1": 1210,
    "resetID": 101,
    "resetNum": 100
  },
  "130142": {
    "id": 130142,
    "hero1": 1319,
    "resetID": 101,
    "resetNum": 100
  },
  "130241": {
    "id": 130241,
    "hero1": 1203,
    "resetID": 101,
    "resetNum": 100
  },
  "130242": {
    "id": 130242,
    "hero1": 1210,
    "resetID": 101,
    "resetNum": 100
  },
  "130541": {
    "id": 130541,
    "hero1": 1310,
    "resetID": 101,
    "resetNum": 100
  },
  "130542": {
    "id": 130542,
    "hero1": 1301,
    "resetID": 101,
    "resetNum": 100
  },
  "130741": {
    "id": 130741,
    "hero1": 1301,
    "resetID": 101,
    "resetNum": 100
  },
  "130742": {
    "id": 130742,
    "hero1": 1319,
    "resetID": 101,
    "resetNum": 100
  },
  "130841": {
    "id": 130841,
    "hero1": 1318,
    "resetID": 101,
    "resetNum": 100
  },
  "130842": {
    "id": 130842,
    "hero1": 1307,
    "resetID": 101,
    "resetNum": 100
  },
  "130941": {
    "id": 130941,
    "hero1": 1217,
    "resetID": 101,
    "resetNum": 100
  },
  "130942": {
    "id": 130942,
    "hero1": 1308,
    "resetID": 101,
    "resetNum": 100
  },
  "131041": {
    "id": 131041,
    "hero1": 1319,
    "resetID": 101,
    "resetNum": 100
  },
  "131042": {
    "id": 131042,
    "hero1": 1301,
    "resetID": 101,
    "resetNum": 100
  },
  "131141": {
    "id": 131141,
    "hero1": 1310,
    "resetID": 101,
    "resetNum": 100
  },
  "131142": {
    "id": 131142,
    "hero1": 1318,
    "resetID": 101,
    "resetNum": 100
  },
  "131241": {
    "id": 131241,
    "hero1": 1313,
    "resetID": 101,
    "resetNum": 100
  },
  "131242": {
    "id": 131242,
    "hero1": 1314,
    "resetID": 101,
    "resetNum": 100
  },
  "131341": {
    "id": 131341,
    "hero1": 1311,
    "resetID": 101,
    "resetNum": 100
  },
  "131342": {
    "id": 131342,
    "hero1": 1318,
    "resetID": 101,
    "resetNum": 100
  },
  "131441": {
    "id": 131441,
    "hero1": 1312,
    "resetID": 101,
    "resetNum": 100
  },
  "131442": {
    "id": 131442,
    "hero1": 1315,
    "resetID": 101,
    "resetNum": 100
  },
  "131541": {
    "id": 131541,
    "hero1": 1319,
    "resetID": 101,
    "resetNum": 100
  },
  "131542": {
    "id": 131542,
    "hero1": 1314,
    "resetID": 101,
    "resetNum": 100
  },
  "131641": {
    "id": 131641,
    "hero1": 1317,
    "resetID": 101,
    "resetNum": 100
  },
  "131642": {
    "id": 131642,
    "hero1": 1318,
    "resetID": 101,
    "resetNum": 100
  },
  "131741": {
    "id": 131741,
    "hero1": 1316,
    "resetID": 101,
    "resetNum": 100
  },
  "131742": {
    "id": 131742,
    "hero1": 1318,
    "resetID": 101,
    "resetNum": 100
  },
  "131841": {
    "id": 131841,
    "hero1": 1308,
    "resetID": 101,
    "resetNum": 100
  },
  "131842": {
    "id": 131842,
    "hero1": 1319,
    "resetID": 101,
    "resetNum": 100
  },
  "131941": {
    "id": 131941,
    "hero1": 1310,
    "resetID": 101,
    "resetNum": 100
  },
  "131942": {
    "id": 131942,
    "hero1": 1301,
    "resetID": 101,
    "resetNum": 100
  },
  "132041": {
    "id": 132041,
    "hero1": 1205,
    "resetID": 101,
    "resetNum": 100
  },
  "132042": {
    "id": 132042,
    "hero1": 1316,
    "resetID": 101,
    "resetNum": 100
  },
  "140141": {
    "id": 140141,
    "hero1": 1411,
    "resetID": 101,
    "resetNum": 100
  },
  "140142": {
    "id": 140142,
    "hero1": 1502,
    "resetID": 101,
    "resetNum": 100
  },
  "140143": {
    "id": 140143,
    "hero1": 1509,
    "resetID": 101,
    "resetNum": 100
  },
  "140241": {
    "id": 140241,
    "hero1": 1421,
    "resetID": 101,
    "resetNum": 100
  },
  "140242": {
    "id": 140242,
    "hero1": 1507,
    "resetID": 101,
    "resetNum": 100
  },
  "140341": {
    "id": 140341,
    "hero1": 1407,
    "resetID": 101,
    "resetNum": 100
  },
  "140342": {
    "id": 140342,
    "hero1": 1420,
    "resetID": 101,
    "resetNum": 100
  },
  "140361": {
    "id": 140361,
    "hero1": 1405,
    "resetID": 101,
    "resetNum": 100
  },
  "140441": {
    "id": 140441,
    "hero1": 1204,
    "resetID": 101,
    "resetNum": 100
  },
  "140442": {
    "id": 140442,
    "hero1": 1414,
    "resetID": 101,
    "resetNum": 100
  },
  "140541": {
    "id": 140541,
    "hero1": 1421,
    "resetID": 101,
    "resetNum": 100
  },
  "140542": {
    "id": 140542,
    "hero1": 1420,
    "resetID": 101,
    "resetNum": 100
  },
  "140641": {
    "id": 140641,
    "hero1": 1315,
    "resetID": 101,
    "resetNum": 100
  },
  "140642": {
    "id": 140642,
    "hero1": 1421,
    "resetID": 101,
    "resetNum": 100
  },
  "140661": {
    "id": 140661,
    "hero1": 1404,
    "resetID": 101,
    "resetNum": 100
  },
  "140741": {
    "id": 140741,
    "hero1": 1420,
    "resetID": 101,
    "resetNum": 100
  },
  "140742": {
    "id": 140742,
    "hero1": 1403,
    "resetID": 101,
    "resetNum": 100
  },
  "141041": {
    "id": 141041,
    "hero1": 1411,
    "resetID": 101,
    "resetNum": 100
  },
  "141042": {
    "id": 141042,
    "hero1": 1507,
    "resetID": 101,
    "resetNum": 100
  },
  "141141": {
    "id": 141141,
    "hero1": 1404,
    "resetID": 101,
    "resetNum": 100
  },
  "141142": {
    "id": 141142,
    "hero1": 1402,
    "resetID": 101,
    "resetNum": 100
  },
  "141241": {
    "id": 141241,
    "hero1": 1210,
    "resetID": 101,
    "resetNum": 100
  },
  "141242": {
    "id": 141242,
    "hero1": 1413,
    "resetID": 101,
    "resetNum": 100
  },
  "141341": {
    "id": 141341,
    "hero1": 1403,
    "resetID": 101,
    "resetNum": 100
  },
  "141342": {
    "id": 141342,
    "hero1": 1412,
    "resetID": 101,
    "resetNum": 100
  },
  "141441": {
    "id": 141441,
    "hero1": 1404,
    "resetID": 101,
    "resetNum": 100
  },
  "141442": {
    "id": 141442,
    "hero1": 1406,
    "resetID": 101,
    "resetNum": 100
  },
  "141541": {
    "id": 141541,
    "hero1": 1414,
    "resetID": 101,
    "resetNum": 100
  },
  "141542": {
    "id": 141542,
    "hero1": 1407,
    "resetID": 101,
    "resetNum": 100
  },
  "141641": {
    "id": 141641,
    "hero1": 1420,
    "resetID": 101,
    "resetNum": 100
  },
  "141642": {
    "id": 141642,
    "hero1": 1415,
    "resetID": 101,
    "resetNum": 100
  },
  "141741": {
    "id": 141741,
    "hero1": 1310,
    "resetID": 101,
    "resetNum": 100
  },
  "141742": {
    "id": 141742,
    "hero1": 1418,
    "resetID": 101,
    "resetNum": 100
  },
  "141841": {
    "id": 141841,
    "hero1": 1404,
    "resetID": 101,
    "resetNum": 100
  },
  "141842": {
    "id": 141842,
    "hero1": 1417,
    "resetID": 101,
    "resetNum": 100
  },
  "141941": {
    "id": 141941,
    "hero1": 1417,
    "resetID": 101,
    "resetNum": 100
  },
  "141942": {
    "id": 141942,
    "hero1": 1414,
    "resetID": 101,
    "resetNum": 100
  },
  "142041": {
    "id": 142041,
    "hero1": 1406,
    "resetID": 101,
    "resetNum": 100
  },
  "142042": {
    "id": 142042,
    "hero1": 1403,
    "resetID": 101,
    "resetNum": 100
  },
  "142141": {
    "id": 142141,
    "hero1": 1310,
    "resetID": 101,
    "resetNum": 100
  },
  "142142": {
    "id": 142142,
    "hero1": 1407,
    "resetID": 101,
    "resetNum": 100
  },
  "142161": {
    "id": 142161,
    "hero1": 1420,
    "resetID": 101,
    "resetNum": 100
  },
  "150141": {
    "id": 150141,
    "hero1": 1410,
    "resetID": 101,
    "resetNum": 100
  },
  "150142": {
    "id": 150142,
    "hero1": 1411,
    "resetID": 101,
    "resetNum": 100
  },
  "150143": {
    "id": 150143,
    "hero1": 1402,
    "resetID": 101,
    "resetNum": 100
  },
  "150241": {
    "id": 150241,
    "hero1": 1411,
    "resetID": 101,
    "resetNum": 100
  },
  "150242": {
    "id": 150242,
    "hero1": 1401,
    "resetID": 101,
    "resetNum": 100
  },
  "150243": {
    "id": 150243,
    "hero1": 1507,
    "resetID": 101,
    "resetNum": 100
  },
  "150341": {
    "id": 150341,
    "hero1": 1418,
    "resetID": 101,
    "resetNum": 100
  },
  "150342": {
    "id": 150342,
    "hero1": 1417,
    "resetID": 101,
    "resetNum": 100
  },
  "150343": {
    "id": 150343,
    "hero1": 1508,
    "resetID": 101,
    "resetNum": 100
  },
  "150361": {
    "id": 150361,
    "hero1": 1510,
    "resetID": 101,
    "resetNum": 100
  },
  "150441": {
    "id": 150441,
    "hero1": 1401,
    "resetID": 101,
    "resetNum": 100
  },
  "150442": {
    "id": 150442,
    "hero1": 1511,
    "resetID": 101,
    "resetNum": 100
  },
  "150443": {
    "id": 150443,
    "hero1": 1510,
    "resetID": 101,
    "resetNum": 100
  },
  "150541": {
    "id": 150541,
    "hero1": 1401,
    "resetID": 101,
    "resetNum": 100
  },
  "150542": {
    "id": 150542,
    "hero1": 1511,
    "resetID": 101,
    "resetNum": 100
  },
  "150543": {
    "id": 150543,
    "hero1": 1509,
    "resetID": 101,
    "resetNum": 100
  },
  "150561": {
    "id": 150561,
    "hero1": 1203,
    "resetID": 101,
    "resetNum": 100
  },
  "150641": {
    "id": 150641,
    "hero1": 1412,
    "resetID": 101,
    "resetNum": 100
  },
  "150642": {
    "id": 150642,
    "hero1": 1413,
    "resetID": 101,
    "resetNum": 100
  },
  "150643": {
    "id": 150643,
    "hero1": 1404,
    "resetID": 101,
    "resetNum": 100
  },
  "150741": {
    "id": 150741,
    "hero1": 1302,
    "resetID": 101,
    "resetNum": 100
  },
  "150742": {
    "id": 150742,
    "hero1": 1412,
    "resetID": 101,
    "resetNum": 100
  },
  "150743": {
    "id": 150743,
    "hero1": 1502,
    "resetID": 101,
    "resetNum": 100
  },
  "150841": {
    "id": 150841,
    "hero1": 1419,
    "resetID": 101,
    "resetNum": 100
  },
  "150842": {
    "id": 150842,
    "hero1": 1404,
    "resetID": 101,
    "resetNum": 100
  },
  "150843": {
    "id": 150843,
    "hero1": 1503,
    "resetID": 101,
    "resetNum": 100
  },
  "150861": {
    "id": 150861,
    "hero1": 1511,
    "resetID": 101,
    "resetNum": 100
  },
  "150941": {
    "id": 150941,
    "hero1": 1401,
    "resetID": 101,
    "resetNum": 100
  },
  "150942": {
    "id": 150942,
    "hero1": 1411,
    "resetID": 101,
    "resetNum": 100
  },
  "150943": {
    "id": 150943,
    "hero1": 1507,
    "resetID": 101,
    "resetNum": 100
  },
  "150961": {
    "id": 150961,
    "hero1": 1502,
    "resetID": 101,
    "resetNum": 100
  },
  "151041": {
    "id": 151041,
    "hero1": 1407,
    "resetID": 101,
    "resetNum": 100
  },
  "151042": {
    "id": 151042,
    "hero1": 1413,
    "resetID": 101,
    "resetNum": 100
  },
  "151043": {
    "id": 151043,
    "hero1": 1511,
    "resetID": 101,
    "resetNum": 100
  },
  "151141": {
    "id": 151141,
    "hero1": 1210,
    "resetID": 101,
    "resetNum": 100
  },
  "151142": {
    "id": 151142,
    "hero1": 1412,
    "resetID": 101,
    "resetNum": 100
  },
  "151143": {
    "id": 151143,
    "hero1": 1509,
    "resetID": 101,
    "resetNum": 100
  },
  "151241": {
    "id": 151241,
    "hero1": 1404,
    "resetID": 101,
    "resetNum": 100
  },
  "151242": {
    "id": 151242,
    "hero1": 1511,
    "resetID": 101,
    "resetNum": 100
  },
  "151243": {
    "id": 151243,
    "hero1": 1510,
    "resetID": 101,
    "resetNum": 100
  },
  "151261": {
    "id": 151261,
    "hero1": "",
    "resetID": 101,
    "resetNum": 100
  },
  "151341": {
    "id": 151341,
    "hero1": 1404,
    "resetID": 101,
    "resetNum": 100
  },
  "151342": {
    "id": 151342,
    "hero1": 1506,
    "resetID": 101,
    "resetNum": 100
  },
  "151343": {
    "id": 151343,
    "hero1": 1507,
    "resetID": 101,
    "resetNum": 100
  },
  "151361": {
    "id": 151361,
    "hero1": "",
    "resetID": 101,
    "resetNum": 100
  },
  "151441": {
    "id": 151441,
    "hero1": 1511,
    "resetID": 101,
    "resetNum": 100
  },
  "151442": {
    "id": 151442,
    "hero1": 1506,
    "resetID": 101,
    "resetNum": 100
  },
  "151443": {
    "id": 151443,
    "hero1": 1504,
    "resetID": 101,
    "resetNum": 100
  },
  "151461": {
    "id": 151461,
    "hero1": 1412,
    "resetID": 101,
    "resetNum": 100
  },
  "151541": {
    "id": 151541,
    "hero1": 1506,
    "resetID": 101,
    "resetNum": 100
  },
  "151542": {
    "id": 151542,
    "hero1": 1507,
    "resetID": 101,
    "resetNum": 100
  },
  "151543": {
    "id": 151543,
    "hero1": 1501,
    "resetID": 101,
    "resetNum": 100
  },
  "151561": {
    "id": 151561,
    "hero1": "",
    "resetID": 101,
    "resetNum": 100
  },
  "151641": {
    "id": 151641,
    "hero1": 1511,
    "resetID": 101,
    "resetNum": 100
  },
  "151642": {
    "id": 151642,
    "hero1": 1510,
    "resetID": 101,
    "resetNum": 100
  },
  "151643": {
    "id": 151643,
    "hero1": 1513,
    "resetID": 101,
    "resetNum": 100
  },
  "151661": {
    "id": 151661,
    "hero1": 1504,
    "resetID": 101,
    "resetNum": 100
  },
  "151741": {
    "id": 151741,
    "hero1": 1315,
    "resetID": 101,
    "resetNum": 100
  },
  "151742": {
    "id": 151742,
    "hero1": 1406,
    "resetID": 101,
    "resetNum": 100
  },
  "151743": {
    "id": 151743,
    "hero1": 1518,
    "resetID": 101,
    "resetNum": 100
  },
  "151841": {
    "id": 151841,
    "hero1": 1406,
    "resetID": 101,
    "resetNum": 100
  },
  "151842": {
    "id": 151842,
    "hero1": 1405,
    "resetID": 101,
    "resetNum": 100
  },
  "151843": {
    "id": 151843,
    "hero1": 1517,
    "resetID": 101,
    "resetNum": 100
  },
  "151941": {
    "id": 151941,
    "hero1": 1407,
    "resetID": 101,
    "resetNum": 100
  },
  "151942": {
    "id": 151942,
    "hero1": 1412,
    "resetID": 101,
    "resetNum": 100
  },
  "151943": {
    "id": 151943,
    "hero1": 1413,
    "resetID": 101,
    "resetNum": 100
  },
  "152041": {
    "id": 152041,
    "hero1": 1318,
    "resetID": 101,
    "resetNum": 100
  },
  "152042": {
    "id": 152042,
    "hero1": 1319,
    "resetID": 101,
    "resetNum": 100
  },
  "152043": {
    "id": 152043,
    "hero1": 1521,
    "resetID": 101,
    "resetNum": 100
  },
  "152141": {
    "id": 152141,
    "hero1": 1407,
    "resetID": 101,
    "resetNum": 100
  },
  "152142": {
    "id": 152142,
    "hero1": 1510,
    "resetID": 101,
    "resetNum": 100
  },
  "152143": {
    "id": 152143,
    "hero1": 1520,
    "resetID": 101,
    "resetNum": 100
  },
  "152241": {
    "id": 152241,
    "hero1": 1404,
    "resetID": 101,
    "resetNum": 100
  },
  "152242": {
    "id": 152242,
    "hero1": 1421,
    "resetID": 101,
    "resetNum": 100
  },
  "152243": {
    "id": 152243,
    "hero1": 1510,
    "resetID": 101,
    "resetNum": 100
  },
  "152341": {
    "id": 152341,
    "hero1": 1421,
    "resetID": 101,
    "resetNum": 100
  },
  "152342": {
    "id": 152342,
    "hero1": 1511,
    "resetID": 101,
    "resetNum": 100
  },
  "152343": {
    "id": 152343,
    "hero1": 1524,
    "resetID": 101,
    "resetNum": 100
  },
  "152441": {
    "id": 152441,
    "hero1": 1420,
    "resetID": 101,
    "resetNum": 100
  },
  "152442": {
    "id": 152442,
    "hero1": 1511,
    "resetID": 101,
    "resetNum": 100
  },
  "152443": {
    "id": 152443,
    "hero1": 1523,
    "resetID": 101,
    "resetNum": 100
  },
  "152541": {
    "id": 152541,
    "hero1": 1420,
    "resetID": 101,
    "resetNum": 100
  },
  "152542": {
    "id": 152542,
    "hero1": 1421,
    "resetID": 101,
    "resetNum": 100
  },
  "152543": {
    "id": 152543,
    "hero1": 1510,
    "resetID": 101,
    "resetNum": 100
  },
  "152641": {
    "id": 152641,
    "hero1": 1421,
    "resetID": 101,
    "resetNum": 100
  },
  "152642": {
    "id": 152642,
    "hero1": 1511,
    "resetID": 101,
    "resetNum": 100
  },
  "152643": {
    "id": 152643,
    "hero1": 1520,
    "resetID": 101,
    "resetNum": 100
  },
  "152741": {
    "id": 152741,
    "hero1": 1406,
    "resetID": 101,
    "resetNum": 100
  },
  "152742": {
    "id": 152742,
    "hero1": 1319,
    "resetID": 101,
    "resetNum": 100
  },
  "152743": {
    "id": 152743,
    "hero1": 1504,
    "resetID": 101,
    "resetNum": 100
  },
  "152841": {
    "id": 152841,
    "hero1": 1525,
    "resetID": 101,
    "resetNum": 100
  },
  "152842": {
    "id": 152842,
    "hero1": 1511,
    "resetID": 101,
    "resetNum": 100
  },
  "152843": {
    "id": 152843,
    "hero1": 1522,
    "resetID": 101,
    "resetNum": 100
  },
  "152941": {
    "id": 152941,
    "hero1": 1419,
    "resetID": 101,
    "resetNum": 100
  },
  "152942": {
    "id": 152942,
    "hero1": 1310,
    "resetID": 101,
    "resetNum": 100
  },
  "152943": {
    "id": 152943,
    "hero1": 1407,
    "resetID": 101,
    "resetNum": 100
  },
  "153041": {
    "id": 153041,
    "hero1": 1526,
    "resetID": 101,
    "resetNum": 100
  },
  "153042": {
    "id": 153042,
    "hero1": 1411,
    "resetID": 101,
    "resetNum": 100
  },
  "153043": {
    "id": 153043,
    "hero1": 1520,
    "resetID": 101,
    "resetNum": 100
  },
  "153141": {
    "id": 153141,
    "hero1": 1521,
    "resetID": 101,
    "resetNum": 100
  },
  "153142": {
    "id": 153142,
    "hero1": 1420,
    "resetID": 101,
    "resetNum": 100
  },
  "153143": {
    "id": 153143,
    "hero1": 1520,
    "resetID": 101,
    "resetNum": 100
  },
  "153241": {
    "id": 153241,
    "hero1": 1522,
    "resetID": 101,
    "resetNum": 100
  },
  "153242": {
    "id": 153242,
    "hero1": 1507,
    "resetID": 101,
    "resetNum": 100
  },
  "153243": {
    "id": 153243,
    "hero1": 1302,
    "resetID": 101,
    "resetNum": 100
  },
  "153341": {
    "id": 153341,
    "hero1": 1310,
    "resetID": 101,
    "resetNum": 100
  },
  "153342": {
    "id": 153342,
    "hero1": 1534,
    "resetID": 101,
    "resetNum": 100
  },
  "153343": {
    "id": 153343,
    "hero1": 1529,
    "resetID": 101,
    "resetNum": 100
  },
  "153441": {
    "id": 153441,
    "hero1": 1217,
    "resetID": 101,
    "resetNum": 100
  },
  "153442": {
    "id": 153442,
    "hero1": 1532,
    "resetID": 101,
    "resetNum": 100
  },
  "153443": {
    "id": 153443,
    "hero1": 1507,
    "resetID": 101,
    "resetNum": 100
  },
  "153541": {
    "id": 153541,
    "hero1": 1418,
    "resetID": 101,
    "resetNum": 100
  },
  "153542": {
    "id": 153542,
    "hero1": 1528,
    "resetID": 101,
    "resetNum": 100
  },
  "153543": {
    "id": 153543,
    "hero1": 1529,
    "resetID": 101,
    "resetNum": 100
  },
  "153641": {
    "id": 153641,
    "hero1": 1320,
    "resetID": 101,
    "resetNum": 100
  },
  "153642": {
    "id": 153642,
    "hero1": 1421,
    "resetID": 101,
    "resetNum": 100
  },
  "153643": {
    "id": 153643,
    "hero1": 1406,
    "resetID": 101,
    "resetNum": 100
  },
  "153741": {
    "id": 153741,
    "hero1": 1417,
    "resetID": 101,
    "resetNum": 100
  },
  "153742": {
    "id": 153742,
    "hero1": 1511,
    "resetID": 101,
    "resetNum": 100
  },
  "153743": {
    "id": 153743,
    "hero1": 1510,
    "resetID": 101,
    "resetNum": 100
  },
  "153841": {
    "id": 153841,
    "hero1": 1521,
    "resetID": 101,
    "resetNum": 100
  },
  "153842": {
    "id": 153842,
    "hero1": 1507,
    "resetID": 101,
    "resetNum": 100
  },
  "153843": {
    "id": 153843,
    "hero1": 1510,
    "resetID": 101,
    "resetNum": 100
  },
  "153941": {
    "id": 153941,
    "hero1": 1533,
    "resetID": 101,
    "resetNum": 100
  },
  "153942": {
    "id": 153942,
    "hero1": 1511,
    "resetID": 101,
    "resetNum": 100
  },
  "153943": {
    "id": 153943,
    "hero1": 1529,
    "resetID": 101,
    "resetNum": 100
  },
  "154041": {
    "id": 154041,
    "hero1": 1504,
    "resetID": 101,
    "resetNum": 100
  },
  "154042": {
    "id": 154042,
    "hero1": 1511,
    "resetID": 101,
    "resetNum": 100
  },
  "154043": {
    "id": 154043,
    "hero1": 1538,
    "resetID": 101,
    "resetNum": 100
  },
  "154141": {
    "id": 154141,
    "hero1": 1302,
    "resetID": 101,
    "resetNum": 100
  },
  "154142": {
    "id": 154142,
    "hero1": 1507,
    "resetID": 101,
    "resetNum": 100
  },
  "154143": {
    "id": 154143,
    "hero1": 1506,
    "resetID": 101,
    "resetNum": 100
  },
  "160141": {
    "id": 160141,
    "hero1": 1506,
    "resetID": 101,
    "resetNum": 100
  },
  "160142": {
    "id": 160142,
    "hero1": 1510,
    "resetID": 101,
    "resetNum": 100
  },
  "160143": {
    "id": 160143,
    "hero1": 1515,
    "resetID": 101,
    "resetNum": 100
  },
  "160241": {
    "id": 160241,
    "hero1": 1407,
    "resetID": 101,
    "resetNum": 100
  },
  "160242": {
    "id": 160242,
    "hero1": 1511,
    "resetID": 101,
    "resetNum": 100
  },
  "160243": {
    "id": 160243,
    "hero1": 1603,
    "resetID": 101,
    "resetNum": 100
  },
  "160341": {
    "id": 160341,
    "hero1": 1407,
    "resetID": 101,
    "resetNum": 100
  },
  "160342": {
    "id": 160342,
    "hero1": 1510,
    "resetID": 101,
    "resetNum": 100
  },
  "160343": {
    "id": 160343,
    "hero1": 1601,
    "resetID": 101,
    "resetNum": 100
  },
  "160441": {
    "id": 160441,
    "hero1": 1421,
    "resetID": 101,
    "resetNum": 100
  },
  "160442": {
    "id": 160442,
    "hero1": 1605,
    "resetID": 101,
    "resetNum": 100
  },
  "160443": {
    "id": 160443,
    "hero1": 1606,
    "resetID": 101,
    "resetNum": 100
  },
  "160541": {
    "id": 160541,
    "hero1": 1510,
    "resetID": 101,
    "resetNum": 100
  },
  "160542": {
    "id": 160542,
    "hero1": 1608,
    "resetID": 101,
    "resetNum": 100
  },
  "160543": {
    "id": 160543,
    "hero1": 1602,
    "resetID": 101,
    "resetNum": 100
  },
  "160641": {
    "id": 160641,
    "hero1": 1511,
    "resetID": 101,
    "resetNum": 100
  },
  "160642": {
    "id": 160642,
    "hero1": 1605,
    "resetID": 101,
    "resetNum": 100
  },
  "160643": {
    "id": 160643,
    "hero1": 1602,
    "resetID": 101,
    "resetNum": 100
  },
  "160741": {
    "id": 160741,
    "hero1": 1205,
    "resetID": 101,
    "resetNum": 100
  },
  "160742": {
    "id": 160742,
    "hero1": 1402,
    "resetID": 101,
    "resetNum": 100
  },
  "160743": {
    "id": 160743,
    "hero1": 1501,
    "resetID": 101,
    "resetNum": 100
  },
  "160841": {
    "id": 160841,
    "hero1": 1518,
    "resetID": 101,
    "resetNum": 100
  },
  "160842": {
    "id": 160842,
    "hero1": 1517,
    "resetID": 101,
    "resetNum": 100
  },
  "160843": {
    "id": 160843,
    "hero1": 1406,
    "resetID": 101,
    "resetNum": 100
  },
  "160941": {
    "id": 160941,
    "hero1": 1510,
    "resetID": 101,
    "resetNum": 100
  },
  "160942": {
    "id": 160942,
    "hero1": 1521,
    "resetID": 101,
    "resetNum": 100
  },
  "160943": {
    "id": 160943,
    "hero1": 1601,
    "resetID": 101,
    "resetNum": 100
  },
  "161041": {
    "id": 161041,
    "hero1": 1511,
    "resetID": 101,
    "resetNum": 100
  },
  "161042": {
    "id": 161042,
    "hero1": 1510,
    "resetID": 101,
    "resetNum": 100
  },
  "161043": {
    "id": 161043,
    "hero1": 1611,
    "resetID": 101,
    "resetNum": 100
  },
  "161141": {
    "id": 161141,
    "hero1": 1522,
    "resetID": 101,
    "resetNum": 100
  },
  "161142": {
    "id": 161142,
    "hero1": 1511,
    "resetID": 101,
    "resetNum": 100
  },
  "161143": {
    "id": 161143,
    "hero1": 1610,
    "resetID": 101,
    "resetNum": 100
  },
  "161241": {
    "id": 161241,
    "hero1": 1511,
    "resetID": 101,
    "resetNum": 100
  },
  "161242": {
    "id": 161242,
    "hero1": 1522,
    "resetID": 101,
    "resetNum": 100
  },
  "161243": {
    "id": 161243,
    "hero1": 1606,
    "resetID": 101,
    "resetNum": 100
  },
  "161341": {
    "id": 161341,
    "hero1": 1521,
    "resetID": 101,
    "resetNum": 100
  },
  "161342": {
    "id": 161342,
    "hero1": 1520,
    "resetID": 101,
    "resetNum": 100
  },
  "161343": {
    "id": 161343,
    "hero1": 1606,
    "resetID": 101,
    "resetNum": 100
  },
  "161441": {
    "id": 161441,
    "hero1": 1520,
    "resetID": 101,
    "resetNum": 100
  },
  "161442": {
    "id": 161442,
    "hero1": 1526,
    "resetID": 101,
    "resetNum": 100
  },
  "161443": {
    "id": 161443,
    "hero1": 1603,
    "resetID": 101,
    "resetNum": 100
  },
  "161541": {
    "id": 161541,
    "hero1": 1511,
    "resetID": 101,
    "resetNum": 100
  },
  "161542": {
    "id": 161542,
    "hero1": 1510,
    "resetID": 101,
    "resetNum": 100
  },
  "161543": {
    "id": 161543,
    "hero1": 1514,
    "resetID": 101,
    "resetNum": 100
  },
  "161641": {
    "id": 161641,
    "hero1": 1526,
    "resetID": 101,
    "resetNum": 100
  },
  "161642": {
    "id": 161642,
    "hero1": 1520,
    "resetID": 101,
    "resetNum": 100
  },
  "161643": {
    "id": 161643,
    "hero1": 1614,
    "resetID": 101,
    "resetNum": 100
  },
  "161741": {
    "id": 161741,
    "hero1": 1406,
    "resetID": 101,
    "resetNum": 100
  },
  "161742": {
    "id": 161742,
    "hero1": 1405,
    "resetID": 101,
    "resetNum": 100
  },
  "161743": {
    "id": 161743,
    "hero1": 1608,
    "resetID": 101,
    "resetNum": 100
  },
  "161841": {
    "id": 161841,
    "hero1": 1528,
    "resetID": 101,
    "resetNum": 100
  },
  "161842": {
    "id": 161842,
    "hero1": 1525,
    "resetID": 101,
    "resetNum": 100
  },
  "161843": {
    "id": 161843,
    "hero1": 1606,
    "resetID": 101,
    "resetNum": 100
  },
  "161941": {
    "id": 161941,
    "hero1": 1421,
    "resetID": 101,
    "resetNum": 100
  },
  "161942": {
    "id": 161942,
    "hero1": 1420,
    "resetID": 101,
    "resetNum": 100
  },
  "161943": {
    "id": 161943,
    "hero1": 1615,
    "resetID": 101,
    "resetNum": 100
  },
  "162041": {
    "id": 162041,
    "hero1": 1529,
    "resetID": 101,
    "resetNum": 100
  },
  "162042": {
    "id": 162042,
    "hero1": 1511,
    "resetID": 101,
    "resetNum": 100
  },
  "162043": {
    "id": 162043,
    "hero1": 1608,
    "resetID": 101,
    "resetNum": 100
  },
  "162141": {
    "id": 162141,
    "hero1": 1526,
    "resetID": 101,
    "resetNum": 100
  },
  "162142": {
    "id": 162142,
    "hero1": 1520,
    "resetID": 101,
    "resetNum": 100
  },
  "162143": {
    "id": 162143,
    "hero1": 1606,
    "resetID": 101,
    "resetNum": 100
  },
  "162241": {
    "id": 162241,
    "hero1": 1407,
    "resetID": 101,
    "resetNum": 100
  },
  "162242": {
    "id": 162242,
    "hero1": 1506,
    "resetID": 101,
    "resetNum": 100
  },
  "162243": {
    "id": 162243,
    "hero1": 1607,
    "resetID": 101,
    "resetNum": 100
  },
  "162341": {
    "id": 162341,
    "hero1": 1532,
    "resetID": 101,
    "resetNum": 100
  },
  "162342": {
    "id": 162342,
    "hero1": 1528,
    "resetID": 101,
    "resetNum": 100
  },
  "162343": {
    "id": 162343,
    "hero1": 1602,
    "resetID": 101,
    "resetNum": 100
  },
  "162441": {
    "id": 162441,
    "hero1": 1531,
    "resetID": 101,
    "resetNum": 100
  },
  "162442": {
    "id": 162442,
    "hero1": 1610,
    "resetID": 101,
    "resetNum": 100
  },
  "162443": {
    "id": 162443,
    "hero1": 1602,
    "resetID": 101,
    "resetNum": 100
  },
  "162541": {
    "id": 162541,
    "hero1": 1520,
    "resetID": 101,
    "resetNum": 100
  },
  "162542": {
    "id": 162542,
    "hero1": 1603,
    "resetID": 101,
    "resetNum": 100
  },
  "162543": {
    "id": 162543,
    "hero1": 1624,
    "resetID": 101,
    "resetNum": 100
  },
  "162641": {
    "id": 162641,
    "hero1": 1528,
    "resetID": 101,
    "resetNum": 100
  },
  "162642": {
    "id": 162642,
    "hero1": 1525,
    "resetID": 101,
    "resetNum": 100
  },
  "162643": {
    "id": 162643,
    "hero1": 1618,
    "resetID": 101,
    "resetNum": 100
  },
  "162741": {
    "id": 162741,
    "hero1": 1535,
    "resetID": 101,
    "resetNum": 100
  },
  "162742": {
    "id": 162742,
    "hero1": 1608,
    "resetID": 101,
    "resetNum": 100
  },
  "162743": {
    "id": 162743,
    "hero1": 1515,
    "resetID": 101,
    "resetNum": 100
  },
  "162841": {
    "id": 162841,
    "hero1": 1535,
    "resetID": 101,
    "resetNum": 100
  },
  "162842": {
    "id": 162842,
    "hero1": 1627,
    "resetID": 101,
    "resetNum": 100
  },
  "162843": {
    "id": 162843,
    "hero1": 1625,
    "resetID": 101,
    "resetNum": 100
  },
  "162941": {
    "id": 162941,
    "hero1": 1537,
    "resetID": 101,
    "resetNum": 100
  },
  "162942": {
    "id": 162942,
    "hero1": 1614,
    "resetID": 101,
    "resetNum": 100
  },
  "162943": {
    "id": 162943,
    "hero1": 1611,
    "resetID": 101,
    "resetNum": 100
  },
  "163041": {
    "id": 163041,
    "hero1": 1511,
    "resetID": 101,
    "resetNum": 100
  },
  "163042": {
    "id": 163042,
    "hero1": 1537,
    "resetID": 101,
    "resetNum": 100
  },
  "163043": {
    "id": 163043,
    "hero1": 1629,
    "resetID": 101,
    "resetNum": 100
  },
  "163141": {
    "id": 163141,
    "hero1": 1511,
    "resetID": 101,
    "resetNum": 100
  },
  "163142": {
    "id": 163142,
    "hero1": 1510,
    "resetID": 101,
    "resetNum": 100
  },
  "163143": {
    "id": 163143,
    "hero1": 1620,
    "resetID": 101,
    "resetNum": 100
  },
  "163241": {
    "id": 163241,
    "hero1": 1521,
    "resetID": 101,
    "resetNum": 100
  },
  "163242": {
    "id": 163242,
    "hero1": 1507,
    "resetID": 101,
    "resetNum": 100
  },
  "163243": {
    "id": 163243,
    "hero1": 1622,
    "resetID": 101,
    "resetNum": 100
  },
  "163341": {
    "id": 163341,
    "hero1": 1529,
    "resetID": 101,
    "resetNum": 100
  },
  "163342": {
    "id": 163342,
    "hero1": 1511,
    "resetID": 101,
    "resetNum": 100
  },
  "163343": {
    "id": 163343,
    "hero1": 1631,
    "resetID": 101,
    "resetNum": 100
  },
  "163441": {
    "id": 163441,
    "hero1": 1418,
    "resetID": 101,
    "resetNum": 100
  },
  "163442": {
    "id": 163442,
    "hero1": 1511,
    "resetID": 101,
    "resetNum": 100
  },
  "163443": {
    "id": 163443,
    "hero1": 1607,
    "resetID": 101,
    "resetNum": 100
  },
  "163541": {
    "id": 163541,
    "hero1": 1421,
    "resetID": 101,
    "resetNum": 100
  },
  "163542": {
    "id": 163542,
    "hero1": 1511,
    "resetID": 101,
    "resetNum": 100
  },
  "163543": {
    "id": 163543,
    "hero1": 1607,
    "resetID": 101,
    "resetNum": 100
  },
  "163641": {
    "id": 163641,
    "hero1": 1510,
    "resetID": 101,
    "resetNum": 100
  },
  "163642": {
    "id": 163642,
    "hero1": 1511,
    "resetID": 101,
    "resetNum": 100
  },
  "163643": {
    "id": 163643,
    "hero1": 1606,
    "resetID": 101,
    "resetNum": 100
  },
  "163741": {
    "id": 163741,
    "hero1": 1519,
    "resetID": 101,
    "resetNum": 100
  },
  "163742": {
    "id": 163742,
    "hero1": 1511,
    "resetID": 101,
    "resetNum": 100
  },
  "163743": {
    "id": 163743,
    "hero1": 1602,
    "resetID": 101,
    "resetNum": 100
  },
  "163841": {
    "id": 163841,
    "hero1": 1540,
    "resetID": 101,
    "resetNum": 100
  },
  "163842": {
    "id": 163842,
    "hero1": 1511,
    "resetID": 101,
    "resetNum": 100
  },
  "163843": {
    "id": 163843,
    "hero1": 1622,
    "resetID": 101,
    "resetNum": 100
  },
  "163941": {
    "id": 163941,
    "hero1": 1421,
    "resetID": 101,
    "resetNum": 100
  },
  "163942": {
    "id": 163942,
    "hero1": 1511,
    "resetID": 101,
    "resetNum": 100
  },
  "163943": {
    "id": 163943,
    "hero1": 1635,
    "resetID": 101,
    "resetNum": 100
  },
  "164041": {
    "id": 164041,
    "hero1": 1526,
    "resetID": 101,
    "resetNum": 100
  },
  "164042": {
    "id": 164042,
    "hero1": 1521,
    "resetID": 101,
    "resetNum": 100
  },
  "164043": {
    "id": 164043,
    "hero1": 1606,
    "resetID": 101,
    "resetNum": 100
  },
  "164141": {
    "id": 164141,
    "hero1": 1511,
    "resetID": 101,
    "resetNum": 100
  },
  "164142": {
    "id": 164142,
    "hero1": 1521,
    "resetID": 101,
    "resetNum": 100
  },
  "164143": {
    "id": 164143,
    "hero1": 1605,
    "resetID": 101,
    "resetNum": 100
  },
  "164241": {
    "id": 164241,
    "hero1": 1535,
    "resetID": 101,
    "resetNum": 100
  },
  "164242": {
    "id": 164242,
    "hero1": 1511,
    "resetID": 101,
    "resetNum": 100
  },
  "164243": {
    "id": 164243,
    "hero1": 1628,
    "resetID": 101,
    "resetNum": 100
  },
  "164341": {
    "id": 164341,
    "hero1": 1510,
    "resetID": 101,
    "resetNum": 100
  },
  "164342": {
    "id": 164342,
    "hero1": 1525,
    "resetID": 101,
    "resetNum": 100
  },
  "164343": {
    "id": 164343,
    "hero1": 1605,
    "resetID": 101,
    "resetNum": 100
  },
  "164441": {
    "id": 164441,
    "hero1": 1510,
    "resetID": 101,
    "resetNum": 100
  },
  "164442": {
    "id": 164442,
    "hero1": 1535,
    "resetID": 101,
    "resetNum": 100
  },
  "164443": {
    "id": 164443,
    "hero1": 1631,
    "resetID": 101,
    "resetNum": 100
  },
  "164541": {
    "id": 164541,
    "hero1": 1511,
    "resetID": 101,
    "resetNum": 100
  },
  "164542": {
    "id": 164542,
    "hero1": 1510,
    "resetID": 101,
    "resetNum": 100
  },
  "164543": {
    "id": 164543,
    "hero1": 1603,
    "resetID": 101,
    "resetNum": 100
  },
  "164641": {
    "id": 164641,
    "hero1": 1501,
    "resetID": 101,
    "resetNum": 100
  },
  "164642": {
    "id": 164642,
    "hero1": 1530,
    "resetID": 101,
    "resetNum": 100
  },
  "164643": {
    "id": 164643,
    "hero1": 1645,
    "resetID": 101,
    "resetNum": 100
  },
  "164741": {
    "id": 164741,
    "hero1": 1511,
    "resetID": 101,
    "resetNum": 100
  },
  "164742": {
    "id": 164742,
    "hero1": 1510,
    "resetID": 101,
    "resetNum": 100
  },
  "164743": {
    "id": 164743,
    "hero1": 1607,
    "resetID": 101,
    "resetNum": 100
  },
  "164841": {
    "id": 164841,
    "hero1": 1508,
    "resetID": 101,
    "resetNum": 100
  },
  "164842": {
    "id": 164842,
    "hero1": 1506,
    "resetID": 101,
    "resetNum": 100
  },
  "164843": {
    "id": 164843,
    "hero1": 1515,
    "resetID": 101,
    "resetNum": 100
  },
  "164941": {
    "id": 164941,
    "hero1": 1511,
    "resetID": 101,
    "resetNum": 100
  },
  "164942": {
    "id": 164942,
    "hero1": 1526,
    "resetID": 101,
    "resetNum": 100
  },
  "164943": {
    "id": 164943,
    "hero1": 1631,
    "resetID": 101,
    "resetNum": 100
  },
  "165041": {
    "id": 165041,
    "hero1": 1532,
    "resetID": 101,
    "resetNum": 100
  },
  "165042": {
    "id": 165042,
    "hero1": 1508,
    "resetID": 101,
    "resetNum": 100
  },
  "165043": {
    "id": 165043,
    "hero1": 1601,
    "resetID": 101,
    "resetNum": 100
  },
  "165141": {
    "id": 165141,
    "hero1": 1510,
    "resetID": 101,
    "resetNum": 100
  },
  "165142": {
    "id": 165142,
    "hero1": 1511,
    "resetID": 101,
    "resetNum": 100
  },
  "165143": {
    "id": 165143,
    "hero1": 1624,
    "resetID": 101,
    "resetNum": 100
  },
  "165241": {
    "id": 165241,
    "hero1": 1421,
    "resetID": 101,
    "resetNum": 100
  },
  "165242": {
    "id": 165242,
    "hero1": 1521,
    "resetID": 101,
    "resetNum": 100
  },
  "165243": {
    "id": 165243,
    "hero1": 1609,
    "resetID": 101,
    "resetNum": 100
  },
  "165341": {
    "id": 165341,
    "hero1": 1503,
    "resetID": 101,
    "resetNum": 100
  },
  "165342": {
    "id": 165342,
    "hero1": 1508,
    "resetID": 101,
    "resetNum": 100
  },
  "165343": {
    "id": 165343,
    "hero1": 1607,
    "resetID": 101,
    "resetNum": 100
  },
  "165441": {
    "id": 165441,
    "hero1": 1532,
    "resetID": 101,
    "resetNum": 100
  },
  "165442": {
    "id": 165442,
    "hero1": 1508,
    "resetID": 101,
    "resetNum": 100
  },
  "165443": {
    "id": 165443,
    "hero1": 1607,
    "resetID": 101,
    "resetNum": 100
  },
  "165541": {
    "id": 165541,
    "hero1": 1532,
    "resetID": 101,
    "resetNum": 100
  },
  "165542": {
    "id": 165542,
    "hero1": 1506,
    "resetID": 101,
    "resetNum": 100
  },
  "165543": {
    "id": 165543,
    "hero1": 1602,
    "resetID": 101,
    "resetNum": 100
  },
  "165641": {
    "id": 165641,
    "hero1": 1510,
    "resetID": 101,
    "resetNum": 100
  },
  "165642": {
    "id": 165642,
    "hero1": 1511,
    "resetID": 101,
    "resetNum": 100
  },
  "165643": {
    "id": 165643,
    "hero1": 1654,
    "resetID": 101,
    "resetNum": 100
  },
  "165741": {
    "id": 165741,
    "hero1": 1421,
    "resetID": 101,
    "resetNum": 100
  },
  "165742": {
    "id": 165742,
    "hero1": 1652,
    "resetID": 101,
    "resetNum": 100
  },
  "165743": {
    "id": 165743,
    "hero1": 1609,
    "resetID": 101,
    "resetNum": 100
  },
  "165841": {
    "id": 165841,
    "hero1": 1503,
    "resetID": 101,
    "resetNum": 100
  },
  "165842": {
    "id": 165842,
    "hero1": 1508,
    "resetID": 101,
    "resetNum": 100
  },
  "165843": {
    "id": 165843,
    "hero1": 1607,
    "resetID": 101,
    "resetNum": 100
  },
  "990141": {
    "id": 990141,
    "hero1": "",
    "resetID": 101,
    "resetNum": 100
  },
  "990142": {
    "id": 990142,
    "hero1": "",
    "resetID": 101,
    "resetNum": 100
  },
  "990143": {
    "id": 990143,
    "hero1": "",
    "resetID": 101,
    "resetNum": 100
  },
  "990241": {
    "id": 990241,
    "hero1": "",
    "resetID": 101,
    "resetNum": 100
  },
  "990242": {
    "id": 990242,
    "hero1": "",
    "resetID": 101,
    "resetNum": 100
  },
  "990243": {
    "id": 990243,
    "hero1": "",
    "resetID": 101,
    "resetNum": 100
  },
  "990341": {
    "id": 990341,
    "hero1": "",
    "resetID": 101,
    "resetNum": 100
  },
  "990342": {
    "id": 990342,
    "hero1": "",
    "resetID": 101,
    "resetNum": 100
  },
  "990343": {
    "id": 990343,
    "hero1": "",
    "resetID": 101,
    "resetNum": 100
  },
  "990441": {
    "id": 990441,
    "hero1": "",
    "resetID": 101,
    "resetNum": 100
  },
  "990442": {
    "id": 990442,
    "hero1": "",
    "resetID": 101,
    "resetNum": 100
  },
  "990443": {
    "id": 990443,
    "hero1": "",
    "resetID": 101,
    "resetNum": 100
  },
  "990541": {
    "id": 990541,
    "hero1": "",
    "resetID": 101,
    "resetNum": 100
  },
  "990542": {
    "id": 990542,
    "hero1": "",
    "resetID": 101,
    "resetNum": 100
  },
  "990543": {
    "id": 990543,
    "hero1": "",
    "resetID": 101,
    "resetNum": 100
  },
  "990641": {
    "id": 990641,
    "hero1": "",
    "resetID": 101,
    "resetNum": 100
  },
  "990642": {
    "id": 990642,
    "hero1": "",
    "resetID": 101,
    "resetNum": 100
  },
  "990643": {
    "id": 990643,
    "hero1": "",
    "resetID": 101,
    "resetNum": 100
  },
  "990741": {
    "id": 990741,
    "hero1": "",
    "resetID": 101,
    "resetNum": 100
  },
  "990742": {
    "id": 990742,
    "hero1": "",
    "resetID": 101,
    "resetNum": 100
  },
  "990743": {
    "id": 990743,
    "hero1": "",
    "resetID": 101,
    "resetNum": 100
  },
  "990841": {
    "id": 990841,
    "hero1": "",
    "resetID": 101,
    "resetNum": 100
  },
  "990842": {
    "id": 990842,
    "hero1": "",
    "resetID": 101,
    "resetNum": 100
  },
  "990843": {
    "id": 990843,
    "hero1": "",
    "resetID": 101,
    "resetNum": 100
  },
  "992141": {
    "id": 992141,
    "hero1": "",
    "resetID": 101,
    "resetNum": 100
  },
  "992142": {
    "id": 992142,
    "hero1": "",
    "resetID": 101,
    "resetNum": 100
  },
  "992143": {
    "id": 992143,
    "hero1": "",
    "resetID": 101,
    "resetNum": 100
  },
  "992241": {
    "id": 992241,
    "hero1": "",
    "resetID": 101,
    "resetNum": 100
  },
  "992242": {
    "id": 992242,
    "hero1": "",
    "resetID": 101,
    "resetNum": 100
  },
  "992243": {
    "id": 992243,
    "hero1": "",
    "resetID": 101,
    "resetNum": 100
  },
  "992341": {
    "id": 992341,
    "hero1": "",
    "resetID": 101,
    "resetNum": 100
  },
  "992342": {
    "id": 992342,
    "hero1": "",
    "resetID": 101,
    "resetNum": 100
  },
  "992343": {
    "id": 992343,
    "hero1": "",
    "resetID": 101,
    "resetNum": 100
  },
  "992441": {
    "id": 992441,
    "hero1": "",
    "resetID": 101,
    "resetNum": 100
  },
  "992442": {
    "id": 992442,
    "hero1": "",
    "resetID": 101,
    "resetNum": 100
  },
  "992443": {
    "id": 992443,
    "hero1": "",
    "resetID": 101,
    "resetNum": 100
  },
  "992541": {
    "id": 992541,
    "hero1": "",
    "resetID": 101,
    "resetNum": 100
  },
  "992542": {
    "id": 992542,
    "hero1": "",
    "resetID": 101,
    "resetNum": 100
  },
  "992543": {
    "id": 992543,
    "hero1": "",
    "resetID": 101,
    "resetNum": 100
  },
  "992641": {
    "id": 992641,
    "hero1": "",
    "resetID": 101,
    "resetNum": 100
  },
  "992642": {
    "id": 992642,
    "hero1": "",
    "resetID": 101,
    "resetNum": 100
  },
  "992643": {
    "id": 992643,
    "hero1": "",
    "resetID": 101,
    "resetNum": 100
  },
  "992741": {
    "id": 992741,
    "hero1": "",
    "resetID": 101,
    "resetNum": 100
  },
  "992742": {
    "id": 992742,
    "hero1": "",
    "resetID": 101,
    "resetNum": 100
  },
  "992743": {
    "id": 992743,
    "hero1": "",
    "resetID": 101,
    "resetNum": 100
  },
  "992841": {
    "id": 992841,
    "hero1": "",
    "resetID": 101,
    "resetNum": 100
  },
  "992842": {
    "id": 992842,
    "hero1": "",
    "resetID": 101,
    "resetNum": 100
  },
  "992843": {
    "id": 992843,
    "hero1": "",
    "resetID": 101,
    "resetNum": 100
  },
  "994141": {
    "id": 994141,
    "hero1": "",
    "resetID": 101,
    "resetNum": 100
  },
  "994142": {
    "id": 994142,
    "hero1": "",
    "resetID": 101,
    "resetNum": 100
  },
  "994143": {
    "id": 994143,
    "hero1": "",
    "resetID": 101,
    "resetNum": 100
  },
  "994241": {
    "id": 994241,
    "hero1": "",
    "resetID": 101,
    "resetNum": 100
  },
  "994242": {
    "id": 994242,
    "hero1": "",
    "resetID": 101,
    "resetNum": 100
  },
  "994243": {
    "id": 994243,
    "hero1": "",
    "resetID": 101,
    "resetNum": 100
  },
  "994341": {
    "id": 994341,
    "hero1": "",
    "resetID": 101,
    "resetNum": 100
  },
  "994342": {
    "id": 994342,
    "hero1": "",
    "resetID": 101,
    "resetNum": 100
  },
  "994343": {
    "id": 994343,
    "hero1": "",
    "resetID": 101,
    "resetNum": 100
  },
  "994441": {
    "id": 994441,
    "hero1": "",
    "resetID": 101,
    "resetNum": 100
  },
  "994442": {
    "id": 994442,
    "hero1": "",
    "resetID": 101,
    "resetNum": 100
  },
  "994443": {
    "id": 994443,
    "hero1": "",
    "resetID": 101,
    "resetNum": 100
  },
  "994541": {
    "id": 994541,
    "hero1": "",
    "resetID": 101,
    "resetNum": 100
  },
  "994542": {
    "id": 994542,
    "hero1": "",
    "resetID": 101,
    "resetNum": 100
  },
  "994543": {
    "id": 994543,
    "hero1": "",
    "resetID": 101,
    "resetNum": 100
  },
  "994641": {
    "id": 994641,
    "hero1": "",
    "resetID": 101,
    "resetNum": 100
  },
  "994642": {
    "id": 994642,
    "hero1": "",
    "resetID": 101,
    "resetNum": 100
  },
  "994643": {
    "id": 994643,
    "hero1": "",
    "resetID": 101,
    "resetNum": 100
  },
  "994741": {
    "id": 994741,
    "hero1": "",
    "resetID": 101,
    "resetNum": 100
  },
  "994742": {
    "id": 994742,
    "hero1": "",
    "resetID": 101,
    "resetNum": 100
  },
  "994743": {
    "id": 994743,
    "hero1": "",
    "resetID": 101,
    "resetNum": 100
  },
  "994841": {
    "id": 994841,
    "hero1": "",
    "resetID": 101,
    "resetNum": 100
  },
  "994842": {
    "id": 994842,
    "hero1": "",
    "resetID": 101,
    "resetNum": 100
  },
  "994843": {
    "id": 994843,
    "hero1": "",
    "resetID": 101,
    "resetNum": 100
  }
}